[
  {
    "text": "Но, главное что работает",
    "score": 12,
    "best_url": "https://wiki.anycubic.com/en/faq",
    "chat_id": -1002295062981,
    "count": 1,
    "ts": 1782217841.323905
  },
  {
    "text": "как обычно надо более точные запросы составлять",
    "score": 12,
    "best_url": "https://wiki.anycubic.com/en/fdm-3d-printer",
    "chat_id": -1002295062981,
    "count": 1,
    "ts": 1782208174.1628487
  },
  {
    "text": "Мало ли у человека есть каптон но нет резинок канцелярских? У меня примерно так",
    "score": 15,
    "best_url": "https://wiki.anycubic.com/en/sn-code",
    "chat_id": -1002295062981,
    "count": 1,
    "ts": 1782207885.8488197
  },
  {
    "text": "Каптоновый скотч, как вариант",
    "score": 11,
    "best_url": "https://wiki.anycubic.com/en/faq",
    "chat_id": -1002295062981,
    "count": 1,
    "ts": 1782207744.2472334
  },
  {
    "text": "Смотрите закрепы, заходите на сайт, админы стараются ж. Собирают инфу, пытаются как то структурировать",
    "score": 29,
    "best_url": "https://wiki.anycubic.com/en/fdm-3d-printer/kobra-neo/kobra-neo-the-model-have-fine-lines",
    "chat_id": -1002295062981,
    "count": 1,
    "ts": 1782205770.7744615
  },
  {
    "text": "[ссылка] Эта ссылка и много другого полезного на сайте в закрепе",
    "score": 25,
    "best_url": "https://wiki.anycubic.com/en/resin-3d-printer/Common/cleaning-and-maintenance-of-the-guide-rails",
    "chat_id": -1002295062981,
    "count": 1,
    "ts": 1782205723.0535302
  },
  {
    "text": "а что в поиске вводить? крышка хотенда?",
    "score": 13,
    "best_url": "https://wiki.anycubic.com/en/fdm-3d-printer",
    "chat_id": -1002295062981,
    "count": 1,
    "ts": 1782205330.9403667
  },
  {
    "text": "Напечатать? Сменил на магнитную. Теперь и орига лежит и новая орига лежит от поддержки",
    "score": 13,
    "best_url": "https://wiki.anycubic.com/en/fdm-3d-printer/kobra-2-pro",
    "chat_id": -1002295062981,
    "count": 1,
    "ts": 1782204267.9621625
  },
  {
    "text": "Напечатать? Сменил на а магнитную. Теперь и орига лежит и новая орига лежит от поддержки",
    "score": 14,
    "best_url": "https://wiki.anycubic.com/en/sn-code",
    "chat_id": -1002295062981,
    "count": 1,
    "ts": 1782204253.7177296
  },
  {
    "text": "Как же он надоел 😂",
    "score": 15,
    "best_url": "https://wiki.anycubic.com/en/creat-ticket",
    "chat_id": -1002295062981,
    "count": 1,
    "ts": 1782200311.1819077
  },
  {
    "text": "Футболки рваные видел сколько стоят?)",
    "score": 11,
    "best_url": "https://wiki.anycubic.com/en/faq",
    "chat_id": -1002295062981,
    "count": 1,
    "ts": 1782200273.9016879
  },
  {
    "text": "Там высота от сопла до борта туалета где-то 3 мм",
    "score": 22,
    "best_url": "https://wiki.anycubic.com/en/resin-3d-printer",
    "chat_id": -1002295062981,
    "count": 1,
    "ts": 1782199974.6526716
  },
  {
    "text": "а смотреть как он из туалета выехать не может это отдельный вид искусства 😂",
    "score": 15,
    "best_url": "https://wiki.anycubic.com/en/error-codes/10131-code",
    "chat_id": -1002295062981,
    "count": 2,
    "ts": 1782219695.4829855
  },
  {
    "text": "Почему не сделали сперва очистку сопла , а потом уже отбивание концевиков и нюхание стола 😁",
    "score": 15,
    "best_url": "https://wiki.anycubic.com/en/error-codes/11530-code/k3",
    "chat_id": -1002295062981,
    "count": 1,
    "ts": 1782199113.3027277
  },
  {
    "text": "Он просто не может выехать из-за того , что сопля петга затвердела",
    "score": 22,
    "best_url": "https://wiki.anycubic.com/en/resin-3d-printer",
    "chat_id": -1002295062981,
    "count": 1,
    "ts": 1782199049.5802488
  },
  {
    "text": "защёлки на крышке уже отжили своё?",
    "score": 13,
    "best_url": "https://wiki.anycubic.com/en/contact-us",
    "chat_id": -1002295062981,
    "count": 2,
    "ts": 1782203325.9339702
  },
  {
    "text": "Ночью встал с1 с перепутом (аса) Так как пробная отпечатка - решил продолжить. 5 часов простоя на паузе дало вот такой дефект на внешке. А в остальном изделие функционально. Посмотрим как будет на рабочем месте",
    "score": 14,
    "best_url": "https://wiki.anycubic.com/en/error-codes/11503-code/kobra-3",
    "chat_id": -1002295062981,
    "count": 1,
    "ts": 1782190389.826599
  },
  {
    "text": "не совсем понял что за бобышки 🤔",
    "score": 14,
    "best_url": "https://wiki.anycubic.com/en/fdm-3d-printer",
    "chat_id": -1002295062981,
    "count": 1,
    "ts": 1782166183.2283003
  },
  {
    "text": "Что делать если катушка тонкая и заваливается набок постоянно",
    "score": 13,
    "best_url": "https://wiki.anycubic.com/en/wash-and-cure",
    "chat_id": -1002295062981,
    "count": 1,
    "ts": 1782165147.041719
  },
  {
    "text": "Что делать",
    "score": 11,
    "best_url": "https://wiki.anycubic.com/en/faq",
    "chat_id": -1002295062981,
    "count": 1,
    "ts": 1782165134.808288
  }
]